{
    "text_report":  "=== QA Report: wordcasefix [2026-06-06 23:00:53] ===\n\n【基础可访问性】\n✅ PASS: 首页HTTP状态码200 → 200\n✅ PASS: 页面标题存在且不为空 → WordCaseFix - Free Online Text, Math \u0026 Developer Tools\n✅ PASS: 页面描述meta存在 → 已找到\n\n【SEO基础】\n✅ PASS: /sitemap.xml 可访问 → 状态码: 200\n✅ PASS: /robots.txt 可访问 → 状态码: 200\n✅ PASS: /ads.txt 可访问 → 状态码: 200\n✅ PASS: 首页canonical标签 → 已找到\n\n【变现相关】\n⚠️ WARN: AdSense广告占位代码 → 未找到广告代码\n         说明：AdSense审核中，审核通过后替换占位代码\n\n【内容质量】\n⚠️ WARN: 工具数量检查 → 无法自动检测工具数量\n         说明：需人工访问网站核实工具数量是否为200\n✅ PASS: 404页面处理 → 不存在的页面正确返回404\n\n总计：8/10 通过\n需要修复：0 项\n建议关注：2 项",
    "project_id":  "wordcasefix",
    "checks":  [
                   {
                       "detail":  "200",
                       "status":  "PASS",
                       "item":  "首页HTTP状态码200"
                   },
                   {
                       "detail":  "WordCaseFix - Free Online Text, Math \u0026 Developer Tools",
                       "status":  "PASS",
                       "item":  "页面标题存在且不为空"
                   },
                   {
                       "detail":  "已找到",
                       "status":  "PASS",
                       "item":  "页面描述meta存在"
                   },
                   {
                       "detail":  "状态码: 200",
                       "status":  "PASS",
                       "item":  "/sitemap.xml 可访问"
                   },
                   {
                       "detail":  "状态码: 200",
                       "status":  "PASS",
                       "item":  "/robots.txt 可访问"
                   },
                   {
                       "detail":  "状态码: 200",
                       "status":  "PASS",
                       "item":  "/ads.txt 可访问"
                   },
                   {
                       "detail":  "已找到",
                       "status":  "PASS",
                       "item":  "首页canonical标签"
                   },
                   {
                       "detail":  "未找到广告代码",
                       "status":  "WARN",
                       "item":  "AdSense广告占位代码",
                       "note":  "AdSense审核中，审核通过后替换占位代码"
                   },
                   {
                       "detail":  "无法自动检测工具数量",
                       "status":  "WARN",
                       "item":  "工具数量检查",
                       "note":  "需人工访问网站核实工具数量是否为200"
                   },
                   {
                       "detail":  "不存在的页面正确返回404",
                       "status":  "PASS",
                       "item":  "404页面处理"
                   }
               ],
    "domain":  "wordcasefix.com",
    "report_time":  "2026-06-06 23:00:53",
    "summary":  {
                    "pass":  8,
                    "fail":  0,
                    "total":  10,
                    "warn":  2
                },
    "project_name":  "wordcasefix"
}
